theia_picker/__init__.py
theia_picker/cli.py
theia_picker/download.py
theia_picker/utils.py
theia_picker-1.2.2.dist-info/LICENSE
theia_picker-1.2.2.dist-info/METADATA
theia_picker-1.2.2.dist-info/WHEEL
theia_picker-1.2.2.dist-info/entry_points.txt
theia_picker-1.2.2.dist-info/top_level.txt
theia_picker-1.2.2.dist-info/RECORD
