Metadata-Version: 2.1
Name: theia-picker
Version: 1.2.2
Summary: Theia picker
Author: Remi Cresson
Author-email: remi.cresson@inrae.fr
License: MIT
Requires-Python: >=3.8
License-File: LICENSE
Requires-Dist: requests
Requires-Dist: pydantic ==2.*
Requires-Dist: urllib3
Requires-Dist: tqdm
